<?xml version="1.0" encoding="UTF-8"?>
<!DOCTYPE suite SYSTEM "https://testng.org/testng-1.0.dtd">
<suite name="Loan department">
		
<!--		Group testing by keyword set which is "Smoke" -->

	<test thread-count="5" name="Regression">
	  <groups>
	  		<run>
	  			<include name="Smoke"></include>
	  		</run>
	  </groups>
		<classes>
			<class name="CH16_TestNG.runTestCaseWithoutJavaCompiler"></class>
			<class name="CH16_TestNG.day2"></class>
			<class name="CH16_TestNG.day4"></class>	
			<class name="CH16_TestNG.day3"></class>
		</classes>
	</test>
</suite> 
